[
    {
        "serial":"1",
        "title":"Blue Crescent Chatroom",
        "techstack":[
            ["./images/tailwind.png","tailwind"],
            ["./images/js.png","js"],
            ["./images/firebase.png","firebase"],
            ["./images/vite.png","vite"]
        ],
        "thumbnail":"./images/chatroom.png",
        "caption":"Simple chat app with user authentication and live messaging",
        "websitelink":"https://publicchatroom.vercel.app",
        "githublink":"https://github.com/kyawkhantlinn/publicchatroom",
        "color":"red"
    },
    {
        "serial":"2",
        "title":"Landing Page",
        "techstack":[
            ["./images/html.svg","html"],
            ["./images/bootstrap.png","bootstrap"],
            ["./images/js.png","js"]
        ],
        "thumbnail":"./images/plannco.png",
        "caption":"A modern, responsive landing page clean layout and smooth animations",
        "websitelink":"https://kyawkhantlinn.github.io/planncoproject",
        "githublink":"https://github.com/kyawkhantlinn/planncoproject",
        "color":"green"
    },
    {
        "serial":"3",
        "title":"Weather App",
        "techstack":[
            ["./images/html.svg","html"],
            ["./images/bootstrap.png","bootstrap"],
            ["./images/js.png","js"]
        ],
        "thumbnail":"./images/weatherapp.png",
        "caption":"Small weather app with city search and 5-day forecast",
        "websitelink":"https://kyawkhantlinn.github.io/weatherapp",
        "githublink":"https://github.com/kyawkhantlinn/weatherapp",
        "color":"blue"
    }
]